turelutils/__init__.py
turelutils/constants.py
turelutils/hash_utils.py
turelutils/menu_utils.py
turelutils/string_utils.py
turelutils/time_utils.py
turelutils/type_utils.py
turelutils-1.0.0.dist-info/licenses/LICENSE
turelutils-1.0.0.dist-info/METADATA
turelutils-1.0.0.dist-info/WHEEL
turelutils-1.0.0.dist-info/top_level.txt
turelutils-1.0.0.dist-info/RECORD
