Metadata-Version: 2.4
Name: turelutils
Version: 1.0.0
Summary: A package with utility functions I use regularly
Author: Arthur Kwak
License: MIT
Requires-Python: >=3.8
License-File: LICENSE
Dynamic: license-file
